custom/__init__.py
custom/admin.py
custom/apps.py
custom/models.py
custom/tests.py
custom/urls.py
custom/views.py
custom/migrations/0001_initial.py
custom/migrations/0002_rename_section_dep_rename_department_studyprogram_and_more.py
custom/migrations/0003_rename_dep_department.py
custom/migrations/0004_remove_area_study_program_delete_faculty_delete_area_and_more.py
custom/migrations/0005_echelon_grade.py
custom/migrations/0006_position_code.py
custom/migrations/0007_adninfo.py
custom/migrations/0008_unit_leader.py
custom/migrations/0009_department_leader.py
custom/migrations/0010_alter_department_unit.py
custom/migrations/0011_alter_unit_leader.py
custom/migrations/0012_alter_department_leader.py
custom/migrations/0013_alter_unit_options.py
custom/migrations/__init__.py
custom/migrations/__pycache__/0001_initial.cpython-310.pyc
custom/migrations/__pycache__/0001_initial.cpython-37.pyc
custom/migrations/__pycache__/0001_initial.cpython-39.pyc
custom/migrations/__pycache__/0002_rename_section_dep_rename_department_studyprogram_and_more.cpython-310.pyc
custom/migrations/__pycache__/0002_rename_section_dep_rename_department_studyprogram_and_more.cpython-37.pyc
custom/migrations/__pycache__/0002_rename_section_dep_rename_department_studyprogram_and_more.cpython-39.pyc
custom/migrations/__pycache__/0003_rename_dep_department.cpython-310.pyc
custom/migrations/__pycache__/0003_rename_dep_department.cpython-37.pyc
custom/migrations/__pycache__/0003_rename_dep_department.cpython-39.pyc
custom/migrations/__pycache__/0004_remove_area_study_program_delete_faculty_delete_area_and_more.cpython-310.pyc
custom/migrations/__pycache__/0004_remove_area_study_program_delete_faculty_delete_area_and_more.cpython-37.pyc
custom/migrations/__pycache__/0004_remove_area_study_program_delete_faculty_delete_area_and_more.cpython-39.pyc
custom/migrations/__pycache__/0005_echelon_grade.cpython-310.pyc
custom/migrations/__pycache__/0005_echelon_grade.cpython-37.pyc
django_ipghrms_custom-1.0.dist-info/LICENSE
django_ipghrms_custom-1.0.dist-info/METADATA
django_ipghrms_custom-1.0.dist-info/WHEEL
django_ipghrms_custom-1.0.dist-info/top_level.txt
django_ipghrms_custom-1.0.dist-info/RECORD
